LICENSE
README.md
jsxn.py
setup.py
jsxn.egg-info/PKG-INFO
jsxn.egg-info/SOURCES.txt
jsxn.egg-info/dependency_links.txt
jsxn.egg-info/top_level.txt
jsxn.egg-info/zip-safe