Metadata-Version: 2.1
Name: jsxn
Version: 0.2
Summary: Python Metaclass JSON library
Home-page: https://github.com/shawcx/jsxn
Author: Matthew Shaw
Author-email: mshaw.cx@gmail.com
License: MIT
Platform: UNKNOWN
Classifier: Development Status :: 4 - Beta
Classifier: License :: OSI Approved :: MIT License
Classifier: Programming Language :: Python :: 3
License-File: LICENSE
